unreal_stylesheet/__init__.py
unreal_stylesheet/icons.qrc
unreal_stylesheet/icons.rcc
unreal_stylesheet/main.py
unreal_stylesheet/ue.qss
unreal_stylesheet/ue.scss
unreal_stylesheet/icons/arrow-down-white.svg
unreal_stylesheet/icons/arrow-down.svg
unreal_stylesheet/icons/arrow-up-white.svg
unreal_stylesheet/icons/arrow-up.svg
unreal_stylesheet/icons/check.svg
unreal_stylesheet/icons/cross-white.svg
unreal_stylesheet/icons/cross.svg
unreal_stylesheet/icons/progress-pattern.svg
unreal_stylesheet/icons/radio.svg
unreal_stylesheet/icons/triangle-down-white.svg
unreal_stylesheet/icons/triangle-down.svg
unreal_stylesheet/icons/triangle-right-white.svg
unreal_stylesheet/icons/triangle-right.svg
unreal_stylesheet/icons/uncheck.svg
unreal_stylesheet/icons/unradio.svg
unreal_stylesheet-0.0.4.dist-info/LICENSE
unreal_stylesheet-0.0.4.dist-info/METADATA
unreal_stylesheet-0.0.4.dist-info/WHEEL
unreal_stylesheet-0.0.4.dist-info/top_level.txt
unreal_stylesheet-0.0.4.dist-info/RECORD
