Metadata-Version: 2.1
Name: unreal-stylesheet
Version: 0.0.4
Summary: style qt like unreal 5
Author: Xingyu Lei, Hannes Delbeke
License: MIT License
Project-URL: Homepage, https://github.com/leixingyu/unrealStylesheet
Project-URL: Source, https://github.com/leixingyu/unrealStylesheet
Keywords: qt,unreal,unrealengine,engine,pyside,pyside2,pyside6,PyQt5,PyQt6,stylesheet,dark,night,theme,darkmode,ui
Classifier: Programming Language :: Python :: 3.7
Requires-Python: >=3.4
License-File: LICENSE
Requires-Dist: importlib-metadata; python_version < "3.7"
